libder/__init__.py
libder/libder.py
libder-0.0.6.dist-info/METADATA
libder-0.0.6.dist-info/WHEEL
libder-0.0.6.dist-info/licenses/LICENSE
libder-0.0.6.dist-info/RECORD
