Metadata-Version: 2.1
Name: libder
Version: 0.0.6
Summary: Der
Project-URL: Homepage, https://pypi.org/project/libder/
Author: Der
License-File: LICENSE
Classifier: License :: OSI Approved :: MIT License
Classifier: Operating System :: OS Independent
Classifier: Programming Language :: Python :: 3
Requires-Python: >=3.7
Requires-Dist: opencv-python
